rorolite/__init__.py
rorolite/config.py
rorolite/deploy.py
rorolite/fabfile.py
rorolite/main.py
rorolite/project.py
rorolite/runtime.py
rorolite/utils.py
rorolite/files/etc/profile.d/rorolite.sh
rorolite/runtimes/python3/runtime.yml
rorolite/runtimes/python3-keras/runtime.yml
rorolite/runtimes/raspberrypi-python3-keras/runtime.yml
rorolite-0.2.3.dist-info/DESCRIPTION.rst
rorolite-0.2.3.dist-info/METADATA
rorolite-0.2.3.dist-info/RECORD
rorolite-0.2.3.dist-info/WHEEL
rorolite-0.2.3.dist-info/entry_points.txt
rorolite-0.2.3.dist-info/metadata.json
rorolite-0.2.3.dist-info/top_level.txt
