Metadata-Version: 2.0
Name: rorolite
Version: 0.2.3
Summary: Command-line tool to deploy ML applications to your own server with a single command
Home-page: UNKNOWN
Author: rorodata
Author-email: rorodata.team@gmail.com
License: UNKNOWN
Platform: UNKNOWN
Requires-Dist: Fabric3 (>=1.13.1.post1)
Requires-Dist: click (==6.7)
Requires-Dist: firefly-python (>=0.1.9)
